{
  "title":"Apple iPhone 16 (Ultramarine, 128 GB)",
  "price":74900,
  "image":"image/iphone.png",
  "rating":{"rate":4.6, "ratings":19560, "reviews":5602},
  "offers":[
    "Bank Offer5% cashback on Flipkart Axis Bank Credit Card upto ₹4,000 per statement quarter",
    "Bank Offer5% cashback on Axis Bank Flipkart Debit Card up to ₹750",
    "Bank OfferFlat ₹10 Instant Cashback on Paytm UPI Trxns. Min Order Value ₹500. Valid once per Paytm account",
    "Special PriceGet extra ₹5000 off (price inclusive of cashback/coupon)",
    "Bank Offer₹4000 Off On ICICI Bank Credit Non EMI, Credit and Debit Card EMI Transactions",
    "Bank Offer₹4000 Off On Kotak Bank Credit Card Transactions."
  ]
}